jumon/__init__.py
jumon-1.2.dev1.dist-info/DESCRIPTION.rst
jumon-1.2.dev1.dist-info/METADATA
jumon-1.2.dev1.dist-info/RECORD
jumon-1.2.dev1.dist-info/WHEEL
jumon-1.2.dev1.dist-info/metadata.json
jumon-1.2.dev1.dist-info/top_level.txt
