Metadata-Version: 2.0
Name: jumon
Version: 1.2.dev1
Summary: The small framework for sub commands.
Home-page: https://github.com/TakesxiSximada/jumon
Author: TakesxiSximada
Author-email: sximada+jumon@gmail.com
License: Apache License 2.0
Platform: any
Classifier: Development Status :: 4 - Beta
Classifier: Intended Audience :: System Administrators
Classifier: License :: OSI Approved :: Apache Software License
Classifier: Programming Language :: Python
Classifier: Programming Language :: Python :: 2.7
Classifier: Programming Language :: Python :: 3.4
Classifier: Programming Language :: Python :: 3.5
Classifier: Programming Language :: Python :: 3.6
Classifier: Topic :: Software Development
Requires-Dist: six
